[
 {
   "Date": "2020-03-19",
   "Open": 19900,
   "High": 20393,
   "Low": 18834,
   "Close": 19853,
   "Adj Close": 19853,
   "Volume": 239922
 },
 {
   "Date": "2020-03-20",
   "Open": 19583,
   "High": 20882,
   "Low": 18825,
   "Close": 19875,
   "Adj Close": 19875,
   "Volume": 285733
 },
 {
   "Date": "2020-03-22",
   "Open": 18504,
   "High": 18507,
   "Low": 18086,
   "Close": 18238,
   "Adj Close": 18238,
   "Volume": 204991
 },
 {
   "Date": "2020-03-23",
   "Open": 18230,
   "High": 19804,
   "Low": 18088,
   "Close": 18745,
   "Adj Close": 18745,
   "Volume": 119535345
 },
 {
   "Date": "2020-03-24",
   "Open": 18987,
   "High": 20943,
   "Low": 18925,
   "Close": 20511,
   "Adj Close": 20511,
   "Volume": 106863898
 },
 {
   "Date": "2020-03-25",
   "Open": 20446,
   "High": 21892,
   "Low": 20279,
   "Close": 21100,
   "Adj Close": 21100,
   "Volume": 130872632
 },
 {
   "Date": "2020-03-26",
   "Open": 20998,
   "High": 22545,
   "Low": 20510,
   "Close": 22492,
   "Adj Close": 22492,
   "Volume": 123364604
 },
 {
   "Date": "2020-03-27",
   "Open": 22123,
   "High": 22321,
   "Low": 21316,
   "Close": 21410,
   "Adj Close": 21410,
   "Volume": 98666789
 },
 {
   "Date": "2020-03-29",
   "Open": 20926,
   "High": 21244,
   "Low": 20778,
   "Close": 21213,
   "Adj Close": 21213,
   "Volume": 711107
 },
 {
   "Date": "2020-03-30",
   "Open": 21350,
   "High": 22250,
   "Low": 21153,
   "Close": 22196,
   "Adj Close": 22196,
   "Volume": 82143599
 },
 {
   "Date": "2020-03-31",
   "Open": 22204,
   "High": 22386,
   "Low": 21470,
   "Close": 21502,
   "Adj Close": 21502,
   "Volume": 66006634
 },
 {
   "Date": "2020-04-01",
   "Open": 21397,
   "High": 21423,
   "Low": 20648,
   "Close": 20932,
   "Adj Close": 20932,
   "Volume": 82218631
 },
 {
   "Date": "2020-04-02",
   "Open": 21030,
   "High": 21374,
   "Low": 20500,
   "Close": 21160,
   "Adj Close": 21160,
   "Volume": 97616148
 },
 {
   "Date": "2020-04-03",
   "Open": 21044,
   "High": 21331,
   "Low": 20740,
   "Close": 20928,
   "Adj Close": 20928,
   "Volume": 63241057
 },
 {
   "Date": "2020-04-06",
   "Open": 21647,
   "High": 22663,
   "Low": 21620,
   "Close": 22555,
   "Adj Close": 22555,
   "Volume": 96739993
 },
 {
   "Date": "2020-04-07",
   "Open": 22496,
   "High": 23477,
   "Low": 22300,
   "Close": 22488,
   "Adj Close": 22488,
   "Volume": 274505
 },
 {
   "Date": "2020-04-08",
   "Open": 22498,
   "High": 23426,
   "Low": 22337,
   "Close": 23417,
   "Adj Close": 23417,
   "Volume": 98632961
 },
 {
   "Date": "2020-04-09",
   "Open": 23267,
   "High": 23889,
   "Low": 23020,
   "Close": 23676,
   "Adj Close": 23676,
   "Volume": 110699818
 },
 {
   "Date": "2020-04-12",
   "Open": 23839,
   "High": 23911,
   "Low": 23108,
   "Close": 23331,
   "Adj Close": 23331,
   "Volume": 816363
 },
 {
   "Date": "2020-04-13",
   "Open": 23295,
   "High": 23609,
   "Low": 22968,
   "Close": 23368,
   "Adj Close": 23368,
   "Volume": 66333180
 },
 {
   "Date": "2020-04-14",
   "Open": 23621,
   "High": 23967,
   "Low": 23534,
   "Close": 23843,
   "Adj Close": 23843,
   "Volume": 75910145
 },
 {
   "Date": "2020-04-15",
   "Open": 23757,
   "High": 23809,
   "Low": 23103,
   "Close": 23211,
   "Adj Close": 23211,
   "Volume": 81277443
 },
 {
   "Date": "2020-04-16",
   "Open": 23265,
   "High": 24327,
   "Low": 23079,
   "Close": 24157,
   "Adj Close": 24157,
   "Volume": 94173258
 },
 {
   "Date": "2020-04-17",
   "Open": 24239,
   "High": 24305,
   "Low": 23701,
   "Close": 24151,
   "Adj Close": 24151,
   "Volume": 105186538
 },
 {
   "Date": "2020-04-19",
   "Open": 23944,
   "High": 24028,
   "Low": 23917,
   "Close": 23970,
   "Adj Close": 23970,
   "Volume": 284615
 },
 {
   "Date": "2020-04-20",
   "Open": 24143,
   "High": 24167,
   "Low": 23441,
   "Close": 23530,
   "Adj Close": 23530,
   "Volume": 87221700
 },
 {
   "Date": "2020-04-21",
   "Open": 23273,
   "High": 23433,
   "Low": 22814,
   "Close": 22999,
   "Adj Close": 22999,
   "Volume": 111731192
 },
 {
   "Date": "2020-04-23",
   "Open": 23315,
   "High": 23772,
   "Low": 23233,
   "Close": 23282,
   "Adj Close": 23282,
   "Volume": 78882561
 },
 {
   "Date": "2020-04-24",
   "Open": 23246,
   "High": 23460,
   "Low": 23166,
   "Close": 23416,
   "Adj Close": 23416,
   "Volume": 9038285
 }
]